mjson5/__init__.py
mjson5/__main__.py
mjson5/arg_parser.py
mjson5/host.py
mjson5/lib.py
mjson5/parser.py
mjson5/tool.py
mjson5/version.py
mjson5-10.9.13.dist-info/METADATA
mjson5-10.9.13.dist-info/WHEEL
mjson5-10.9.13.dist-info/entry_points.txt
mjson5-10.9.13.dist-info/top_level.txt
mjson5-10.9.13.dist-info/RECORD
