Metadata-Version: 2.1
Name: mjson5
Version: 10.9.13
Summary: A Python implementation of the JSON5 data format.
Home-page: https://github.com/leeHeisen/mjson5.git
Author: Dirk Pranke
Author-email: leeheisen@126.com
License: Apache
Platform: UNKNOWN
Classifier: Development Status :: 5 - Production/Stable
Classifier: Intended Audience :: Developers
Classifier: License :: OSI Approved :: Apache Software License
Classifier: Programming Language :: Python :: 2
Classifier: Programming Language :: Python :: 2.7
Classifier: Programming Language :: Python :: 3
Classifier: Programming Language :: Python :: 3.8
Classifier: Programming Language :: Python :: 3.9
Classifier: Programming Language :: Python :: 3.10
Classifier: Programming Language :: Python :: 3.11
Provides-Extra: dev
Requires-Dist: hypothesis ; extra == 'dev'
